isa_rwval-0.10.11.dist-info/licenses/LICENSE.txt
isatools/__init__.py
isatools/__main__.py
isatools/isajson.py
isatools/isatab.py
isatools/isatab_full.py
isatools/isatab_meta.py
isatools/isaviz.py
isatools/model.py
isatools/errors/__init__.py
isatools/resources/isatools.ini
isatools/resources/config/xml/cellcount_flowcytometry.xml
isatools/resources/config/xml/cellsorting_flowcyt.xml
isatools/resources/config/xml/clinical_chemistry.xml
isatools/resources/config/xml/copynumvariation_micro.xml
isatools/resources/config/xml/dnamethylation_micro.xml
isatools/resources/config/xml/dnamethylation_seq.xml
isatools/resources/config/xml/envgen_survey_seq.xml
isatools/resources/config/xml/genome_seq.xml
isatools/resources/config/xml/hematology.xml
isatools/resources/config/xml/heterozygosity_micro.xml
isatools/resources/config/xml/histology.xml
isatools/resources/config/xml/histonemodification_seq.xml
isatools/resources/config/xml/investigation.xml
isatools/resources/config/xml/metaboliteprofiling_ms.xml
isatools/resources/config/xml/metaboliteprofiling_nmr.xml
isatools/resources/config/xml/metagenome_seq.xml
isatools/resources/config/xml/ppi_detection_micro.xml
isatools/resources/config/xml/protein_dna_binding_ident_micro.xml
isatools/resources/config/xml/protein_dna_binding_ident_seq.xml
isatools/resources/config/xml/protein_expression_ge.xml
isatools/resources/config/xml/protein_expression_micro.xml
isatools/resources/config/xml/protein_expression_ms.xml
isatools/resources/config/xml/proteinident_ms.xml
isatools/resources/config/xml/snpanalysis_micro.xml
isatools/resources/config/xml/studySample.xml
isatools/resources/config/xml/tfbsident_micro.xml
isatools/resources/config/xml/tfbsident_seq.xml
isatools/resources/config/xml/transcription_micro.xml
isatools/resources/config/xml/transcription_rtpcr.xml
isatools/resources/config/xml/transcription_seq.xml
isatools/resources/schemas/isa_model_version_1_0_schemas/core/assay_schema.json
isatools/resources/schemas/isa_model_version_1_0_schemas/core/comment_schema.json
isa_rwval-0.10.11.dist-info/METADATA
isa_rwval-0.10.11.dist-info/WHEEL
isa_rwval-0.10.11.dist-info/top_level.txt
isa_rwval-0.10.11.dist-info/RECORD
