Metadata-Version: 2.4
Name: isa-rwval
Version: 0.10.11
Summary: Metadata tracking tools help to manage an increasingly diverse set of life science, environmental and biomedical experiments
Author-email: ISA Infrastructure Team <isatools@googlegroups.com>
License-Expression: CPAL-1.0
Project-URL: Homepage, https://isa-tools.org/
Project-URL: Documentation, https://isa-tools.org/isa-api/
Project-URL: Repository, https://github.com/ISA-tools/isa-rwval
Classifier: Development Status :: 4 - Beta
Classifier: Intended Audience :: Developers
Classifier: Intended Audience :: Science/Research
Classifier: Intended Audience :: System Administrators
Classifier: Topic :: Scientific/Engineering :: Bio-Informatics
Classifier: Programming Language :: Python :: 3
Classifier: Programming Language :: Python :: 3.9
Classifier: Programming Language :: Python :: 3.10
Classifier: Programming Language :: Python :: 3.11
Classifier: Programming Language :: Python :: 3.12
Classifier: Programming Language :: Python :: 3.13
Requires-Python: >=3.9
License-File: LICENSE.txt
Requires-Dist: networkx>=2.5
Provides-Extra: viz
Requires-Dist: matplotlib; extra == "viz"
Provides-Extra: tables
Requires-Dist: numpy; extra == "tables"
Requires-Dist: pandas; extra == "tables"
Dynamic: license-file
